mpl_skia_pathops/__init__.py
mpl_skia_pathops/_version.py
mpl_skia_pathops/mpl_pe_pathops.py
mpl_skia_pathops/mpl_pe_pathops_deprecated.py
mpl_skia_pathops/mpl_skia_pathops.py
mpl_skia_pathops/mpl_skia_pathops_helper.py
mpl_skia_pathops/pe_skia_shadow.py
mpl_skia_pathops/tests/__init__.py
mpl_skia_pathops/tests/test_example.py
mpl_skia_pathops-0.4.0.dist-info/licenses/LICENSE
mpl_skia_pathops-0.4.0.dist-info/METADATA
mpl_skia_pathops-0.4.0.dist-info/WHEEL
mpl_skia_pathops-0.4.0.dist-info/top_level.txt
mpl_skia_pathops-0.4.0.dist-info/RECORD
