Metadata-Version: 2.4
Name: mpl_skia_pathops
Version: 0.4.0
Home-page: https://github.com/leejjoon/mpl-skia-pathops
Author: leejjoon
Author-email: lee.j.joon@gmail.com
License: BSD 3-Clause
License-File: LICENSE
Requires-Dist: matplotlib
Requires-Dist: skia-pathops
Requires-Dist: mpl-visual-context
Provides-Extra: test
Requires-Dist: black; extra == "test"
Requires-Dist: pytest; extra == "test"
Requires-Dist: pytest-mpl; extra == "test"
Provides-Extra: doc
Requires-Dist: sphinx; extra == "doc"
Requires-Dist: numpydoc; extra == "doc"
Requires-Dist: sphinx_rtd_theme; extra == "doc"
Requires-Dist: sphinx-copybutton; extra == "doc"
Requires-Dist: sphinx-autobuild; extra == "doc"
Requires-Dist: sphinx_gallery>=0.8.2; extra == "doc"
Requires-Dist: autoapi; extra == "doc"
Requires-Dist: mplcyberpunk; extra == "doc"
Provides-Extra: dev
Requires-Dist: black; extra == "dev"
Requires-Dist: pytest; extra == "dev"
Requires-Dist: pytest-mpl; extra == "dev"
Requires-Dist: sphinx; extra == "dev"
Requires-Dist: numpydoc; extra == "dev"
Requires-Dist: sphinx_rtd_theme; extra == "dev"
Requires-Dist: sphinx-copybutton; extra == "dev"
Requires-Dist: sphinx-autobuild; extra == "dev"
Requires-Dist: sphinx_gallery>=0.8.2; extra == "dev"
Requires-Dist: autoapi; extra == "dev"
Requires-Dist: mplcyberpunk; extra == "dev"
Dynamic: license-file
